ASqrtC.py
asqrtc-3.1.1.dist-info/licenses/LICENSE
asqrtc-3.1.1.dist-info/METADATA
asqrtc-3.1.1.dist-info/WHEEL
asqrtc-3.1.1.dist-info/top_level.txt
asqrtc-3.1.1.dist-info/RECORD
